<?xml version="1.0" encoding="utf-8"?>
<!DOCTYPE list SYSTEM "tree.dtd">
<!--AUTHOR: Bonux-->
<list>
	<abilities_settings min_level="85" maximun_points="26" refresh_price="500000000"/>
	<ability_skill_tree>
		<!--Стражник-->
		<skill id="19233" level="1" name="Щит Стражника"/>
		<skill id="19233" level="2" name="Щит Стражника"/>
		<skill id="19233" level="3" name="Щит Стражника"/>
		<skill id="19234" level="1" name="Магический Барьер Стражника"/>
		<skill id="19234" level="2" name="Магический Барьер Стражника"/>
		<skill id="19234" level="3" name="Магический Барьер Стражника"/>
		<skill id="19235" level="1" name="Благословение Тела Стражника"/>
		<skill id="19235" level="2" name="Благословение Тела Стражника"/>
		<skill id="19235" level="3" name="Благословение Тела Стражника"/>
		<skill id="19236" level="1" name="Стихийное Укрытие Стражника"/>
		<skill id="19236" level="2" name="Стихийное Укрытие Стражника"/>
		<skill id="19236" level="3" name="Стихийное Укрытие Стражника"/>
		<skill id="19237" level="1" name="Защитная Броня Стражника"/>
		<skill id="19237" level="2" name="Защитная Броня Стражника"/>
		<skill id="19238" level="1" name="Защитная Кожа Стражника"/>
		<skill id="19238" level="2" name="Защитная Кожа Стражника"/>
		<skill id="19239" level="1" name="Защитная Туника Стражника"/>
		<skill id="19239" level="2" name="Защитная Туника Стражника"/>
		<skill id="19240" level="1" name="Сопротивление Стражника"/>
		<skill id="19240" level="2" name="Сопротивление Стражника"/>
		<skill id="19241" level="1" name="Жизнь Стражника"/>
		<skill id="19241" level="2" name="Жизнь Стражника"/>
		<skill id="19241" level="3" name="Жизнь Стражника"/>
		<skill id="19241" level="4" name="Жизнь Стражника"/>
		<skill id="19242" level="1" name="Блок Стражника"/>
		<skill id="19243" level="1" name="Броня Стражника"/>
		<skill id="19243" level="2" name="Броня Стражника"/>
		<skill id="19243" level="3" name="Броня Стражника"/>
		<skill id="19243" level="4" name="Броня Стражника"/>
		<skill id="19244" level="1" name="Наведение Стражника"/>
		<skill id="19245" level="1" name="Смертоносный Щит Стражника"/>
		<skill id="19245" level="2" name="Смертоносный Щит Стражника"/>
		<skill id="19246" level="1" name="Фокусировка Щита Стражника"/>
		<skill id="19246" level="2" name="Фокусировка Щита Стражника"/>
		<skill id="19247" level="1" name="Контроль Разума Стражника"/>
		<skill id="19247" level="2" name="Контроль Разума Стражника"/>
		<skill id="19248" level="1" name="Благословение Стражника"/>
		<skill id="19248" level="2" name="Благословение Стражника"/>
		<skill id="19249" level="1" name="Сковывающее Укрытие Стражника"/>
		<skill id="19249" level="2" name="Сковывающее Укрытие Стражника"/>
		<skill id="19250" level="1" name="Дух Стражника"/>
		<skill id="19251" level="1" name="Потенциал Стражника"/>
		<skill id="19252" level="1" name="Мастерское Зелье Стражника"/>
		<skill id="19252" level="2" name="Мастерское Зелье Стражника"/>
		<skill id="19253" level="1" name="Искусство Защиты Стражника"/>
		<!--Берсерк-->
		<skill id="19254" level="1" name="Ускорение Берсерка"/>
		<skill id="19254" level="2" name="Ускорение Берсерка"/>
		<skill id="19255" level="1" name="Могущество Берсерка"/>
		<skill id="19255" level="2" name="Могущество Берсерка"/>
		<skill id="19255" level="3" name="Могущество Берсерка"/>
		<skill id="19255" level="4" name="Могущество Берсерка"/>
		<skill id="19256" level="1" name="Стихийная Атака Берсерка"/>
		<skill id="19256" level="2" name="Стихийная Атака Берсерка"/>
		<skill id="19256" level="3" name="Стихийная Атака Берсерка"/>
		<skill id="19256" level="4" name="Стихийная Атака Берсерка"/>
		<skill id="19257" level="1" name="Искусство Фокусировки Берсерка"/>
		<skill id="19257" level="2" name="Искусство Фокусировки Берсерка"/>
		<skill id="19257" level="3" name="Искусство Фокусировки Берсерка"/>
		<skill id="19258" level="1" name="Коварство Берсерка"/>
		<skill id="19258" level="2" name="Коварство Берсерка"/>
		<skill id="19259" level="1" name="Фокусировка Берсерка"/>
		<skill id="19259" level="2" name="Фокусировка Берсерка"/>
		<skill id="19259" level="3" name="Фокусировка Берсерка"/>
		<skill id="19260" level="1" name="Расход Берсерка"/>
		<skill id="19261" level="1" name="Искусство Смерти Берсерка"/>
		<skill id="19261" level="2" name="Искусство Смерти Берсерка"/>
		<skill id="19261" level="3" name="Искусство Смерти Берсерка"/>
		<skill id="19262" level="1" name="Беспощадность Берсерка"/>
		<skill id="19262" level="2" name="Беспощадность Берсерка"/>
		<skill id="19263" level="1" name="Шепот Смерти Берсерка"/>
		<skill id="19263" level="2" name="Шепот Смерти Берсерка"/>
		<skill id="19263" level="3" name="Шепот Смерти Берсерка"/>
		<skill id="19264" level="1" name="Орел Берсерка"/>
		<skill id="19265" level="1" name="Битва Берсерка"/>
		<skill id="19265" level="2" name="Битва Берсерка"/>
		<skill id="19266" level="1" name="Огонь Берсерка"/>
		<skill id="19266" level="2" name="Огонь Берсерка"/>
		<skill id="19267" level="1" name="Ускорение Умений Берсерка"/>
		<skill id="19268" level="1" name="Благословение Берсерка"/>
		<skill id="19268" level="2" name="Благословение Берсерка"/>
		<skill id="19269" level="1" name="Сковывающая Атака Берсерка"/>
		<skill id="19269" level="2" name="Сковывающая Атака Берсерка"/>
		<skill id="19270" level="1" name="Божественная Атака Берсерка"/>
		<skill id="19270" level="2" name="Божественная Атака Берсерка"/>
		<skill id="19271" level="1" name="Мастерское Зелье Берсерка"/>
		<skill id="19271" level="2" name="Мастерское Зелье Берсерка"/>
		<skill id="19272" level="1" name="Боевое Мастерство Берсерка"/>
		<!--Маг-->
		<skill id="19273" level="1" name="Проницательность Мага"/>
		<skill id="19273" level="2" name="Проницательность Мага"/>
		<skill id="19274" level="1" name="Воодушевление Мага"/>
		<skill id="19274" level="2" name="Воодушевление Мага"/>
		<skill id="19274" level="3" name="Воодушевление Мага"/>
		<skill id="19275" level="1" name="Стихийный Выстрел Мага"/>
		<skill id="19275" level="2" name="Стихийный Выстрел Мага"/>
		<skill id="19275" level="3" name="Стихийный Выстрел Мага"/>
		<skill id="19276" level="1" name="Дикая Магия Мага"/>
		<skill id="19276" level="2" name="Дикая Магия Мага"/>
		<skill id="19276" level="3" name="Дикая Магия Мага"/>
		<skill id="19277" level="1" name="Правило Мага"/>
		<skill id="19277" level="2" name="Правило Мага"/>
		<skill id="19277" level="3" name="Правило Мага"/>
		<skill id="19278" level="1" name="Экономия Евы Мага"/>
		<skill id="19279" level="1" name="Мистик Мага"/>
		<skill id="19279" level="2" name="Мистик Мага"/>
		<skill id="19279" level="3" name="Мистик Мага"/>
		<skill id="19280" level="1" name="Протуберанец Мага"/>
		<skill id="19280" level="2" name="Протуберанец Мага"/>
		<skill id="19281" level="1" name="Взгляд Мага"/>
		<skill id="19282" level="1" name="Защита Мага"/>
		<skill id="19282" level="2" name="Защита Мага"/>
		<skill id="19283" level="1" name="Вода Мага"/>
		<skill id="19283" level="2" name="Вода Мага"/>
		<skill id="19284" level="1" name="Ускорение Магии Мага"/>
		<skill id="19284" level="2" name="Ускорение Магии Мага"/>
		<skill id="19285" level="1" name="Благословение Мага"/>
		<skill id="19285" level="2" name="Благословение Мага"/>
		<skill id="19286" level="1" name="Сковывающий Выстрел Мага"/>
		<skill id="19286" level="2" name="Сковывающий Выстрел Мага"/>
		<skill id="19287" level="1" name="Божественный Выстрел Мага"/>
		<skill id="19287" level="2" name="Божественный Выстрел Мага"/>
		<skill id="19288" level="1" name="Мастерское Зелье Мага"/>
		<skill id="19288" level="2" name="Мастерское Зелье Мага"/>
		<skill id="19289" level="1" name="Магическое Мастерство Мага"/>
	</ability_skill_tree>
</list>