<?xml version="1.0" encoding="UTF-8"?>
<list xmlns:xsi="http://www.w3.org/2001/XMLSchema-instance" xsi:noNamespaceSchemaLocation="../xsd/multisell.xsd">
	<item>
		<ingredient id="57" count="350000000" />
		<production id="17430" count="1" /> <!-- Eternal Helmet -->
	</item>
	<item>
		<ingredient id="57" count="350000000" />
		<production id="17431" count="1" /> <!-- Eternal Breastplate -->
	</item>
	<item>
		<ingredient id="57" count="350000000" />
		<production id="17432" count="1" /> <!-- Eternal Gaiters -->
	</item>
	<item>
		<ingredient id="57" count="350000000" />
		<production id="17433" count="1" /> <!-- Eternal Gauntlets -->
	</item>
	<item>
		<ingredient id="57" count="350000000" />
		<production id="17434" count="1" /> <!-- Eternal Boots -->
	</item>
	<item>
		<ingredient id="57" count="350000000" />
		<production id="17436" count="1" /> <!-- Eternal Leather Helmet -->
	</item>
	<item>
		<ingredient id="57" count="350000000" />
		<production id="17437" count="1" /> <!-- Eternal Leather Armor -->
	</item>
	<item>
		<ingredient id="57" count="350000000" />
		<production id="17438" count="1" /> <!-- Eternal Leather Leggings -->
	</item>
	<item>
		<ingredient id="57" count="350000000" />
		<production id="17439" count="1" /> <!-- Eternal Leather Gloves -->
	</item>
	<item>
		<ingredient id="57" count="350000000" />
		<production id="17440" count="1" /> <!-- Eternal Leather Boots -->
	</item>
	<item>
		<ingredient id="57" count="350000000" />
		<production id="17441" count="1" /> <!-- Eternal Circlet -->
	</item>
	<item>
		<ingredient id="57" count="350000000" />
		<production id="17442" count="1" /> <!-- Eternal Tunic -->
	</item>
	<item>
		<ingredient id="57" count="350000000" />
		<production id="17443" count="1" /> <!-- Eternal Stockings -->
	</item>
	<item>
		<ingredient id="57" count="350000000" />
		<production id="17444" count="1" /> <!-- Eternal Gloves -->
	</item>
	<item>
		<ingredient id="57" count="350000000" />
		<production id="17445" count="1" /> <!-- Eternal Shoes -->
	</item>
</list>
