<?xml version="1.0" encoding="UTF-8"?>
<list xmlns:xsi="http://www.w3.org/2001/XMLSchema-instance" xsi:noNamespaceSchemaLocation="../xsd/multisell.xsd">
	<npcs>
		<npc>-1</npc>
	</npcs>
	<item>
		<ingredient id="57" count="20000000" />
		<production id="23240" count="1" /> <!-- Pa'agrio's Shirt -->
	</item>
	<item>
		<ingredient id="57" count="20000000" />
		<production id="23301" count="1" /> <!-- Sayha's Shirt -->
	</item>
	<item>
		<ingredient id="57" count="20000000" />
		<production id="23304" count="1" /> <!-- Eva's Shirt -->
	</item>
	<item>
		<ingredient id="57" count="20000000" />
		<production id="23307" count="1" /> <!-- Maphr's Shirt -->
	</item>
	<item>
		<ingredient id="57" count="20000000" />
		<production id="21580" count="1" /> <!-- Power Shirt -->
	</item>
	<item>
		<ingredient id="57" count="20000000" />
		<production id="37718" count="1" /> <!-- Shiny Elemental Shirt -->
	</item>
	<item>
		<ingredient id="57" count="20000000" />
		<production id="23241" count="1" /> <!-- Blessed Scroll: Enchant Elemental Shirt -->
	</item>
	<item>
		<ingredient id="57" count="20000000" />
		<production id="21582" count="1" /> <!-- Blessed Scroll: Enchant Power Shirt -->
	</item>
	<item>
		<ingredient id="57" count="20000000" />
		<production id="47392" count="1" /> <!-- Shining Scroll: Enchant Elemental Shirt -->
	</item>
	<!-- ================= Модификаторы футболок (адена 100000000) ================= -->
	<item>
		<ingredient id="57" count="20000000" />
		<production id="47804" count="1" /> <!-- Слабый Свиток: Модифицировать Футболку -->
	</item>
	<item>
		<ingredient id="57" count="20000000" />
		<production id="47805" count="1" /> <!-- Сияющий Свиток: Модифицировать Футболку -->
	</item>
</list>
